{
    "fecha_ultimo_guardado": "15\/03\/2026",
    "cuentas": [
        {
            "seccion": "Crear cuenta",
            "items": [
                {
                    "nombreOriginal": "Adela Cristaldo",
                    "Deuda": "500.000",
                    "Garante": "Sin Garante",
                    "NCuotas": "6",
                    "Frecuencia": "Viernes",
                    "Transferencia": "Si"
                },
                {
                    "nombreOriginal": "Adriana Amarilla",
                    "Deuda": "10.000.000",
                    "Garante": "Sin Garante",
                    "NCuotas": "",
                    "Frecuencia": "",
                    "Transferencia": "No"
                },
                {
                    "nombreOriginal": "Adriana Ovando",
                    "Deuda": "650.000",
                    "Garante": "Sin Garante",
                    "NCuotas": "",
                    "Frecuencia": "",
                    "Transferencia": "No"
                }
            ]
        }
    ],
    "Pagos": {},
    "Gastos": {}
}