{
    "fecha_ultimo_guardado": "06\/07\/2026",
    "cuentas": [
        {
            "seccion": "Crear cuenta",
            "items": [
                {
                    "nombreOriginal": "Fermin Lopez",
                    "Deuda": "1.000.000",
                    "Garante": "Sin Garante",
                    "NCuotas": "6",
                    "Frecuencia": "Sábado",
                    "Transferencia": "No"
                },
                {
                    "nombreOriginal": "Inocencia Gonzalez",
                    "Deuda": "1.000.000",
                    "Garante": "Sin Garante",
                    "NCuotas": "6",
                    "Frecuencia": "Lunes",
                    "Transferencia": "No"
                },
                {
                    "nombreOriginal": "Claudio Nicolas Aguilar",
                    "Deuda": "400.000",
                    "Garante": "Sin Garante",
                    "NCuotas": "2",
                    "Frecuencia": "Quincenal",
                    "Transferencia": "No"
                },
                {
                    "nombreOriginal": "Noelia Gonzalez Cano",
                    "Deuda": "1.500.000",
                    "Garante": "Sin Garante",
                    "NCuotas": "10",
                    "Frecuencia": "Lunes",
                    "Transferencia": "No"
                },
                {
                    "nombreOriginal": "Alfredo Castillo",
                    "Deuda": "2.200.000",
                    "Garante": "Sin Garante",
                    "NCuotas": "1",
                    "Frecuencia": "Mensual",
                    "Transferencia": "Si"
                },
                {
                    "nombreOriginal": "Dorca Zarza",
                    "Deuda": "1.000.000",
                    "Garante": "Sin Garante",
                    "NCuotas": "1",
                    "Frecuencia": "Mensual",
                    "Transferencia": "Si"
                },
                {
                    "nombreOriginal": "Dorca Zarza 2",
                    "Deuda": "1.000.000",
                    "Garante": "Sin Garante",
                    "NCuotas": "1",
                    "Frecuencia": "Mensual",
                    "Transferencia": "Si"
                },
                {
                    "nombreOriginal": "Ordonia Davalos",
                    "Deuda": "500.000",
                    "Garante": "Sin Garante",
                    "NCuotas": "6",
                    "Frecuencia": "Sábado",
                    "Transferencia": "No"
                },
                {
                    "nombreOriginal": "Santiago Pereira",
                    "Deuda": "2.000.000",
                    "Garante": "hija",
                    "NCuotas": "1",
                    "Frecuencia": "Mensual",
                    "Transferencia": "Si"
                },
                {
                    "nombreOriginal": "Claudio Insfran",
                    "Deuda": "500.000",
                    "Garante": "Sin Garante",
                    "NCuotas": "1",
                    "Frecuencia": "Mensual",
                    "Transferencia": "No"
                }
            ]
        }
    ],
    "Pagos": {
        "Edgar Fleitas. 100.000*23. Lu": {
            "sigpago": "13\/07\/2026"
        },
        "Edgar Fleitas. 140.000*10. Lu": {
            "sigpago": "13\/07\/2026"
        },
        "Felicia Dominguez. 220.000*6. Sa": {
            "sigpago": "11\/07\/2026"
        },
        "Mirna Cardenas. 2.600.000*6. Ju": {
            "sigpago": "09\/07\/2026"
        },
        "Vanesa Servian. Aire. 100.000*30. Sa": {
            "sigpago": "11\/07\/2026"
        },
        "Vanesa Servian. Lavarropa. 100.000*28. Sa": {
            "sigpago": "11\/07\/2026"
        },
        "Carlos Garcete. 220.000*6. Ju. C1": {
            "sigpago": "08\/07\/2026"
        },
        "Delcia Castillo. Marcelo. 280.000*10. Sa": {
            "sigpago": "09\/07\/2026",
            "NoTCuota": 0,
            "NoTInteres": 0,
            "TCuota": 0,
            "TInteres": 80000
        },
        "Emilse Mercado. 140.000*10. Sa": {
            "NoTCuota": 0,
            "NoTInteres": 0,
            "TCuota": 140000,
            "TInteres": 0
        },
        "Maria Pereira. 600.000. C2": {
            "NoTCuota": 0,
            "NoTInteres": 0,
            "TCuota": 0,
            "TInteres": 100000
        },
        "Maria Pereira. 600.000": {
            "NoTCuota": 0,
            "NoTInteres": 0,
            "TCuota": 0,
            "TInteres": 100000
        },
        "Fermin Lopez. 220.000*6. Sa": {
            "NoTCuota": 220000,
            "NoTInteres": 0,
            "TCuota": 0,
            "TInteres": 0
        },
        "Ignacio Insfran. 380.000. Sa": {
            "sigpago": "08\/07\/2026",
            "NoTCuota": 0,
            "NoTInteres": 0,
            "TCuota": 80000,
            "TInteres": 0
        },
        "Claudio Nicolas Aguilar. 140.000*10. Sa": {
            "NoTCuota": 400000,
            "NoTInteres": 0,
            "TCuota": 0,
            "TInteres": 0
        },
        "Jose Carlos Pintos. 110.000*6. Sa": {
            "NoTCuota": 0,
            "NoTInteres": 0,
            "TCuota": 110000,
            "TInteres": 0
        },
        "Flaminio Gonzalez. 630.000*10. Lu": {
            "sigpago": "08\/07\/2026",
            "NoTCuota": 0,
            "NoTInteres": 0,
            "TCuota": 600000,
            "TInteres": 0
        },
        "Aldo Alcaraz. 1.200.000": {
            "NoTCuota": 0,
            "NoTInteres": 0,
            "TCuota": 0,
            "TInteres": 200000
        },
        "Dorca Zarza. 476.000*10. Mi": {
            "NoTCuota": 0,
            "NoTInteres": 0,
            "TCuota": 476000,
            "TInteres": 0
        },
        "Elsa Cañete. 60.000*44": {
            "NoTCuota": 0,
            "NoTInteres": 0,
            "TCuota": 80000,
            "TInteres": 0
        },
        "Elsa Cañete. 60.000*44. C1": {
            "NoTCuota": 0,
            "NoTInteres": 0,
            "TCuota": 60000,
            "TInteres": 0
        },
        "Elsa Cañete. 60.000*44. C2": {
            "NoTCuota": 0,
            "NoTInteres": 0,
            "TCuota": 60000,
            "TInteres": 0
        },
        "Noelia Gonzalez Cano. 210.000*10. Lu": {
            "NoTCuota": 1050000,
            "NoTInteres": 0,
            "TCuota": 0,
            "TInteres": 0
        },
        "Alfredo Castillo. 2.310.000. Vi": {
            "NoTCuota": 0,
            "NoTInteres": 0,
            "TCuota": 2310000,
            "TInteres": 0
        },
        "Elsa Cañete. 600.000": {
            "sigpago": "09\/07\/2026"
        },
        "Elena Flores. Cristian. 200.000*7. Lu": {
            "sigpago": "09\/07\/2026"
        },
        "Yasmil Franciely Zelaya. 210.000*10. Lu": {
            "NoTCuota": 0,
            "NoTInteres": 0,
            "TCuota": 210000,
            "TInteres": 0
        },
        "Dorca Zarza. 1.100.000. Ju": {
            "NoTCuota": 0,
            "NoTInteres": 0,
            "TCuota": 1100000,
            "TInteres": 0
        },
        "Dorca Zarza. 1.100.000. Mi": {
            "NoTCuota": 1100000,
            "NoTInteres": 0,
            "TCuota": 0,
            "TInteres": 0
        },
        "Dorca Zarza. 1.200.000": {
            "NoTCuota": 0,
            "NoTInteres": 0,
            "TCuota": 0,
            "TInteres": 200000
        },
        "Hugo Careres. Olier. 300.000*2. C1": {
            "NoTCuota": 0,
            "NoTInteres": 50000,
            "TCuota": 0,
            "TInteres": 0
        },
        "Hugo Careres. Olier. 300.000*2. C2": {
            "NoTCuota": 0,
            "NoTInteres": 50000,
            "TCuota": 0,
            "TInteres": 0
        },
        "Ruth. Olier. Qui. C1. 300.000*2": {
            "sigpago": "07\/07\/2026",
            "NoTCuota": 0,
            "NoTInteres": 50000,
            "TCuota": 0,
            "TInteres": 0
        },
        "Ruth. Olier. Qui. C2. 300.000*2": {
            "NoTCuota": 0,
            "NoTInteres": 50000,
            "TCuota": 0,
            "TInteres": 0
        },
        "Cristobal Muñoz. 250.000*6. Sa. C1": {
            "NoTCuota": 250000,
            "NoTInteres": 0,
            "TCuota": 0,
            "TInteres": 0
        },
        "Recordatorio. Cuentas": {
            "NoTCuota": 0,
            "NoTInteres": 0,
            "TCuota": 0,
            "TInteres": 0,
            "sigpago": "Pagado"
        },
        "Juan Alberto Venialgo. 2.000.000*6. Lu": {
            "NoTCuota": 2000000,
            "NoTInteres": 0,
            "TCuota": 0,
            "TInteres": 0
        },
        "Claudio Insfran. 110.000": {
            "NoTCuota": 0,
            "NoTInteres": 0,
            "TCuota": 110000,
            "TInteres": 0
        },
        "Claudio Insfran. 360.000": {
            "NoTCuota": 0,
            "NoTInteres": 0,
            "TCuota": 360000,
            "TInteres": 0
        },
        "Claudio Insfran. 240.000. C1": {
            "NoTCuota": 0,
            "NoTInteres": 0,
            "TCuota": 240000,
            "TInteres": 0
        },
        "Claudio Insfran. 440.000": {
            "NoTCuota": 0,
            "NoTInteres": 0,
            "TCuota": 240000,
            "TInteres": 0
        }
    },
    "Gastos": {
        "yerba": {
            "valor": 18000,
            "accion": "sumar"
        },
        "cuentas": {
            "valor": 1902000,
            "accion": "sumar"
        },
        "farmacia ": {
            "valor": 243000,
            "accion": "sumar"
        }
    }
}