{
    "fecha_creacion": "26/03/2026",
    "lista": {
        "Amelia": {
            "Diario": [
                "Catalina Santacruz. 45.000*44. C1",
                "Cynthia Carolina Baez. 15.000*44",
                "Cynthia Carolina Baez. 15.000*44. C2",
                "Cynthia Carolina Baez. 15.000*44. C3",
                "Cynthia Carolina Baez. 15.000*44. C4",
                "Delfina Britez. 120.000*44",
                "Delfina Britez. 120.000*44. C1",
                "Delfina Britez. 150.000*44. C1",
                "Delfina Britez. 150.000*44. C2",
                "Delfina Britez. 90.000*44. C1",
                "Edilberto Benitez. 80.000*30. C1",
                "Gilberto Molinas. 150.000*44",
                "Graciela Vargas. 30.000*44",
                "Mateo Garcete. Esposa. 42.000*50",
                "Teresa de Fernandez. 120.000*30"
            ],
            "Mensual": [],
            "Quincenal": [
                "Blas Martinez. 840.000*5",
                "Maria Rodas. 440.000*3",
                "Pedro Orue. 220.000*3"
            ],
            "Semanal": [
                "Catalina Santacruz. 98.000*10. Ju",
                "Claudia Gomez. Hna. 140.000*10. Ju",
                "Crispin Rolon. 140.000*10. Ju",
                "Fredy Pintos. 140.000*10. Ju",
                "Ilsa Santacruz. 200.000*7. Ju",
                "Joel Paredes. 400.000*6. Ju",
                "Kateri Mareco Rios. 210.000*10. Ju",
                "Victoria Romero. 280.000*10. Ju"
            ],
            "Atrasados": [
                "Candido Cabral. 220.000*6. Ma",
                "Candido Cabral. 220.000*6. Sa",
                "Claudia Gomez. 140.000*10. Sa",
                "Claudia Gomez. 140.000*10. Sa. C2",
                "Claudia Gomez. 70.000*10. Sa",
                "Cristhian Pedroso. 700.000*5",
                "Deida Gaete. 140.000*10. Ma. C1",
                "Diego Armando. 220.000*6. Sa",
                "Edgar Erique Cuevas. 400.000*7. Lu",
                "Edgar Martinez. Mario Medina. 280.000*10. Sa",
                "Estanislaa Villar. 700.000*8. Mi",
                "Eusebio Mongues. 140.000*10. Ma",
                "Florinda Blanco. Alejandro. 2.800.000*5",
                "Florinda Blanco. Laura. 200.000*12. Sa",
                "Gilmar Rich. 1.100.000. Vi",
                "Graciela Vargas. Heladera. 100.000*29. Vi",
                "Helida Ortiz. 280.000*10. Lu",
                "Hugo Ariel Arrua. 175.000*8. Sa",
                "Hugo Ariel Arrua. 175.000*8. Sa. C2",
                "Hugo Ariel Arrua. 350.000*8. Mi",
                "Hugo Servian. 210.000*10. Mi",
                "Ilsa Santacruz. 200.000*7. Mi",
                "Irma Raquel Cantero. 265.000*8. Ma",
                "Irma Raquel Cantero. 350.000*10. Sa",
                "Javier Mesa. 700.000*4",
                "Jorge Villaverde. Celular. 100.000*20. Ma",
                "Juan Carlos Flores. 280.000*10. Sa",
                "Laureana Insfran. 130.000*6. Lu",
                "Laureana Insfran. Liz. 110.000*6. Lu",
                "Laureana Insfran. Yerna. 220.000*6. Lu",
                "Leonarda Baez. Estela. 210.000*10. Ma",
                "Lido Maciel. Celular. 100.000*19. Sa",
                "Lido Maciel. Helacera. 150.000*28. Sa",
                "Lido Maciel. Lavarropa. 150.000*38. Sa",
                "Liz Mabel Sosa. 330.000*6. Sa",
                "Lizandro Villalba. 210.000*10. Lu",
                "Luana Sosa. 280.000*10. Lu",
                "Marciano Cerdan. 140.000*10. Sa",
                "Marciano Cerdan. Liz. 280.000*5",
                "Mario Medina. Esposa. 420.000*5",
                "Mateo Garcete. 210.000*10. Lu",
                "Miguel Pascual Alfonzo. Emilce. 840.000*5",
                "Miguel Pascual. 12.000.000",
                "Mirian Cardozo. Cristian. 490.000*10. Ma",
                "Mirna Ortiz. 140.000*10. Vi",
                "Nora. Deida. 1.790.000. Sa",
                "Oscar Pacheco. 145.000*7. Vi",
                "Quintana. 500.000*6",
                "Recordatorio 2. Rush. 1",
                "Robert Luis Benitez. 210.000*10. Sa",
                "Salvio Alvarenga. Celular. 100.000*16. Mi",
                "Vicenta Gonzalez. 150.000*6. Vi",
                "Zulma Peralta. 140.000*10. Sa. C2",
                "Gloria Amada Gomez. Pedido"
            ]
        },
        "Felix": {
            "Diario": [
                "Elsa Cañete. 60.000*44",
                "Elsa Cañete. 60.000*44. C1",
                "Elsa Cañete. 60.000*44. C3"
            ],
            "Mensual": [
                "Alfredo Castillo. 1.560.000"
            ],
            "Quincenal": [
                "Esteban Velazquez. 220.000*3",
                "Juan Albino. 1.100.000",
                "Juan Albino. 420.000*5",
                "Karen Gonzalez. 420.000*5",
                "Sonia Amarilla. 220.000*3"
            ],
            "Semanal": [
                "Dorca Zarza. 2.100.000. Ju",
                "Isaias Castillo. 550.000. Ju",
                "Nelva Colman. 350.000*8. Ju",
                "Paola Insfran. 110.000. Ju"
            ],
            "Atrasados": [
                "Alfonzo Cabral. 175.000*6. Lu",
                "Alfredo Castillo. 280.000",
                "Alfredo Castillo. 1.200.000. C2",
                "Armando Santacruz. 1.000.000*9",
                "Bruno Davalos. 220.000*3",
                "Cristobal Muños. 1.100.000",
                "Fabiola Lopez. 100.000*21. Proyector. Mi",
                "Fabiola Lopez. 200.000*37. Aspiradora. Mi",
                "Fabiola Lopez. 300.000*38. Hidro. Mi",
                "Fabiola Lopez. 700.000*10. Mi",
                "Fabiola Lopez. Aire. 150.000*34. Sa",
                "Fatima Fonseca. 140.000*10. Sa",
                "Hugo Caceres. 180.000*4. Sa",
                "Hugo Caceres. Olier. 1.080.000",
                "Hugo Caceres. Olier. 105.000*4",
                "Hugo Caceres. Olier. C2. 480.000",
                "Hugo Marmori. 1.200.000. C2",
                "Liz Paola Mancuello. 140.000*10. Lu",
                "Liz Paola Mancuello. 140.000*10. Sa",
                "Liz Paola Mancuello. 70.000*10. Sa",
                "Mirna Cardenas. 1.000.000*6. Mi",
                "Mirna Gauto. 1.100.000",
                "Paola Insfran. 275.000. Ma",
                "Pedro Franco. 50.000*7. Ma",
                "Pedro Franco. 700.000*10. Mi",
                "Pedro Franco. Aire. 100.000*32. Mi",
                "Ramona Ortiz. 300.000*3",
                "Recordatorio 1. Electro. 1. Mi",
                "Ruth. Olier. Qui. C1. 300.000*2"
            ]
        },
        "Saul": {
            "Diario": [
                "Ana Torres. 150.000*44",
                "Anibal Godoy. 40.000*30",
                "Clyde Isabel Justiniano. 20.000*33",
                "Elva Mateus. 30.000*44",
                "Gedalia DelValle. 180.000*30",
                "Ignacio Melgarejo. 20.000*30",
                "Leopoldo Pereira. 90.000*44",
                "Lourdes Arce. 120.000*30",
                "Luis Arzamendia. 140.000*43",
                "Maria Francisca. 30.000*44",
                "Maria Gauto. 15.000*44",
                "Nanci Milton. 30.000*44. C1",
                "Narciso Achar. 105.000*44",
                "Ordonia Davalos. 25.000*24",
                "Ordonia Davalos. 50.000*24. C1",
                "Rosalba Gonzalez Duarte. 15.000*44",
                "Thais Orquiola. Cesar Solis. 30.000*44"
            ],
            "Mensual": [],
            "Quincenal": [
                "Cyntia Mendoza. 700.000*4",
                "Noelia Gonzalez Cano. Celular. 300.000*13",
                "Porfirio Sanabria. 560.000*5",
                "Reinaldo Narvae. 440.000*3"
            ],
            "Semanal": [
                "Alcides Rodas. 440.000*6. Ju",
                "Arcadio Benitez. 280.000*10. Ju",
                "Claudelina Maldonado. 140.000*10. Ju",
                "Diego Dure. 220.000*6. Ju",
                "Gloria Cristaldo. Celular. 100.000*16. Ju",
                "Leonardo Dure. 220.000*6. Ju",
                "Lourdes Arce. 280.000*10. Ju",
                "Maria Antonia Caballero. 100.000*23. Ju",
                "Pablina Velazquez. 140.000*10. Ju",
                "Shirley Candia. Antonia Baez. 110.000*6. Ju",
                "Tomasa Cantero. Lavarropa. 100.000*28. Ju"
            ],
            "Atrasados": [
                "Adriana Amarilla. 220.000*6. Lu",
                "Alcides Rodas. 100.000*36. Lu",
                "Alejandro Martinez. 280.000*10. Mi",
                "Angelina Forcado. 140.000*10. Mi",
                "Blas Guereño. 440.000*3",
                "Carlos Garcete. 220.000*6. Mi",
                "Celia Gimenez. 280.000*10. Mi",
                "Cesar Solis. 100.000*23. Ma",
                "Cesar Solis. 100.000*33. Lu",
                "Cesar Solis. 100.000*34. Sa",
                "Cesar Solis. 280.000*10. Lu",
                "Claudelina Lopez. 110.000*6. Mi",
                "Denis Coronel. 220.000*10. Lu",
                "Denis de Oliveira. 990.000*8. Mi",
                "Elizardo Coronel. 200.000*7. Sa",
                "Elsa Florentin. 300.000*24. Sa",
                "Felicia Dominguez. Amiga. 220.000*6. Sa",
                "Fermin Lopez. 220.000*6. Sa",
                "Francisca Gomez. 140.000*10. Sa",
                "Fredy Espinoza. 468.000*10. Sa",
                "Hugo Cabral. 140.000*10. Vi",
                "Hugo Cabral. 70.000*10. Lu",
                "Jessica Cabral. 440.000*6. Lu",
                "Jhon Eguzquiza. 550.000",
                "Juan Delgado. 2.000.000*6. Lu",
                "Juan Delgado. 2.150.000. Mi",
                "Juan Raimundo. 220.000*3",
                "Juan Raimundo. 220.000*3. C2",
                "Juan Ricardo Martinez. 100.000*27. Sa",
                "Juan Ricardo Martinez. 140.000*10. Lu",
                "Lalia Barrios. 280.000*10. Lu",
                "Leonarda Zalazar. 220.000*6. Lu",
                "Liliana Olmedo. 70.000*10. Sa",
                "Liz Mabel Dure. 1.100.000*6. Mi",
                "Maria Antonia Caballero. Heladera. 100.000*29. Lu",
                "Maria Elsa Benitez. 140.000*10. Sa",
                "Maria Francisca. 110.000*6. Mi",
                "Maria Magdalena. 560.000*10. Sa",
                "Modesto Caceres. 560.000*5",
                "Norma Beatriz Blanco. 140.000*10. Lu",
                "Norma Beatriz Blanco. 98.000*10. Vi",
                "Ovidio Ortiz. 210.000*10. Lu",
                "Ruth Mendez Olmedo. 140.000*10. Lu",
                "Ruth Olmedo. 140.000*10. Vi. C2",
                "Ruth Olmedo. 70.000*10. Mi",
                "Ruth Olmedo. 70.000*10. Vi. C2",
                "Sandra Agüero. 140.000*10. Vi",
                "Saul Cardenas. Amiga. 110.000*6. Lu. C1",
                "Sonia Larrea. 110.000*6. Sa",
                "Sonia Larrea. Marido. 140.000*10. Sa",
                "Vanesa Servian. 220.000*6. Mi",
                "Wilfrido Maldonado. 200.000*7. Ma"
            ]
        }
    }
}