{
    "fecha_ultimo_guardado": "22\/07\/2026",
    "cuentas": [],
    "Pagos": {
        "De las Nieves Lopez. 280.000*10. Lu": {
            "NoTCuota": 0,
            "NoTInteres": 0,
            "TCuota": 280000,
            "TInteres": 0
        },
        "Daniel Saucedo Zaya. 440.000*3": {
            "NoTCuota": 880000,
            "NoTInteres": 0,
            "TCuota": 0,
            "TInteres": 0
        },
        "Adriana Hobeker. Planchita. 75.000*19. Mi": {
            "NoTCuota": 0,
            "NoTInteres": 0,
            "TCuota": 75000,
            "TInteres": 0
        },
        "Jose Augusto Cantero. Ronald. 220.000*6. Sa": {
            "NoTCuota": 0,
            "NoTInteres": 0,
            "TCuota": 220000,
            "TInteres": 0
        },
        "Jose Augusto Cantero. 560.000*10. Sa": {
            "NoTCuota": 0,
            "NoTInteres": 0,
            "TCuota": 0,
            "TInteres": 0,
            "Error": "11 pago"
        }
    },
    "Gastos": {}
}