{
    "fecha_ultimo_guardado": "13\/05\/2026",
    "cuentas": [],
    "Pagos": {
        "Nelson Enciso. 210.000*10. Ma": {
            "NoTCuota": 0,
            "NoTInteres": 0,
            "TCuota": 210000,
            "TInteres": 0
        },
        "Miguel Escobar. 440.000*3": {
            "NoTCuota": 0,
            "NoTInteres": 0,
            "TCuota": 0,
            "TInteres": 100000
        },
        "Angela Roa. 140.000*10. Sa. C1": {
            "NoTCuota": 140000,
            "NoTInteres": 0,
            "TCuota": 0,
            "TInteres": 0
        },
        "Angela Roa. 210.000*10. Sa": {
            "NoTCuota": 210000,
            "NoTInteres": 0,
            "TCuota": 0,
            "TInteres": 0
        },
        "Santiago Garcia. 110.000*6. Mi": {
            "NoTCuota": 110000,
            "NoTInteres": 0,
            "TCuota": 0,
            "TInteres": 0
        },
        "Laureana Insfran. Yerno. 110.000*6. Ma": {
            "NoTCuota": 110000,
            "NoTInteres": 0,
            "TCuota": 0,
            "TInteres": 0
        },
        "Maria Matilde Romero. 280.000*10. Lu": {
            "NoTCuota": 180000,
            "NoTInteres": 0,
            "TCuota": 0,
            "TInteres": 0
        },
        "Santiago Pereira. 70.000*10. Mi": {
            "NoTCuota": 70000,
            "NoTInteres": 0,
            "TCuota": 0,
            "TInteres": 0
        }
    },
    "Gastos": {}
}